{
    "Accountant": {
        "label": "Accountant"
    },
    "Defendant": {
        "label": "Defendant"
    },
    "Third Party Defendant": {
        "label": "Third Party Defendant",
        "alt_label": ["3rd Pty Defendant","ThirdParty Defendant","3rd Party Defendant","Third Pty Defendant","3rdParty Defendant","Third-Party Defendant"]
    },
    "Third Party Cross Defendant": {
        "label": "Third Party Cross Defendant",
        "alt_label": ["3rd Pty Cross Defendant","ThirdParty Cross Defendant","3rd Party Cross Defendant","Third Pty Cross Defendant","3rdParty Cross Defendant","Third-Party Cross Defendant"]
    },
    "Third Party Plaintiff": {
        "label": "Third Party Plaintiff",
        "alt_label": ["3rd Party Plaintiff","ThirdParty Plaintiff","3rdParty Plaintiff","3rd Pty Plaintiff","Third Pty Plaintiff","Third-Party Plaintiff"]
    },
    "Amicus": {
        "label": "Amicus"
    },
    "Appellant": {
        "label": "Appellant"
    },
    "Appellee": {
        "label": "Appellee"
    },
    "Appraiser": {
        "label": "Appraiser"
    },
    "Arbitrator": {
        "label": "Arbitrator"
    },
    "Assistant U.S. Trustee": {
        "label": "Assistant U.S. Trustee"
    },
    "Attorney": {
        "label": "Attorney"
    },
    "Auctioneer": {
        "label": "Auctioneer"
    },
    "Auditor": {
        "label": "Auditor"
    },
    "Broker": {
        "label": "Broker"
    },
    "Claimant": {
        "label": "Claimant"
    },
    "Consolidated Claimant": {
        "label": "Consolidated Claimant",
        "alt_label": ["Consol Claimant"]
    },
    "Consolidated Counter Claimant": {
        "label": "Consolidated Counter Claimant",
        "alt_label": ["Consol Counter Claimant","Counter Claimant Consolidated"]
    },
    "Consolidated Counter Defendant": {
        "label": "Consolidated Counter Defendant",
        "alt_label": ["Consol Counter Defendant","Counter Defendant Consolidated"]
    },
    "Consolidated Cross Claimant": {
        "label": "Consolidated Cross Claimant",
        "alt_label": ["Consol Cross Claimant","Consol X-Claimant","Consolidated X-Claimant"]
    },
    "Consolidated Cross Defendant": {
        "label": "Consolidated Cross Defendant",
        "alt_label": ["Consol Cross Defendant","Consol X-Defendant","Consolidated X-Defendant"]
    },
    "Consolidated Defendant": {
        "label": "Consolidated Defendant",
        "alt_label": ["Consol Defendant","Defendant Consolidated","Defendant - Consolidated"]
    },
    "Consolidated Plaintiff": {
        "label": "Consolidated Plaintiff",
        "alt_label": ["Consol Plaintiff","Plaintiff Consolidated","Plaintiff - Consolidated"]
    },
    "Consolidated Third Party": {
        "label": "Consolidated Third Party",
        "alt_label": ["Consol Third Party","Consol ThirdParty","Consol 3rd Party","Consolidated ThirdParty","Consolidated 3rd Party","Consolidated 3rdParty","Consol 3rdParty"]
    },
    "Consolidated Third Party Plaintiff": {
        "label": "Consolidated Third Party Plaintiff",
        "alt_label": ["Consol Third Party Plaintiff","Consol ThirdParty Plaintiff","Consol 3rd Party Plaintiff","Consolidated ThirdParty Plaintiff","Consolidated 3rd Party Plaintiff","Consolidated 3rdParty Plaintiff","Consol 3rdParty Plaintiff"]
    },
    "Consultant": {
        "label": "Consultant"
    },
    "Consumer Privacy": {
        "label": "Consumer Privacy"
    },
    "Counter Claimant": {
        "label": "Counter Claimant",
        "alt_label": ["Counter-Claimant"]
    },
    "Counter Defendant": {
        "label": "Counter Defendant",
        "alt_label": ["Counter-Defendant"]
    },
    "Counter Plaintiff": {
        "label": "Counter Plaintiff",
        "alt_label": ["Counter-Plaintiff"]
    },
    "Creditor": {
        "label": "Creditor"
    },
    "Creditor Committee": {
        "label": "Creditor Committee"
    },
    "Creditor Committee Chair": {
        "label": "Creditor Committee Chair"
    },
    "Cross Appellant": {
        "label": "Cross Appellant",
        "alt_label": ["Cross-Appellant","X-Appellant"]
    },
    "Cross Appellee": {
        "label": "Cross Appellee",
        "alt_label": ["Cross-Appellee","X-Appellee"]
    },
    "Cross Claimant": {
        "label": "Cross Claimant",
        "alt_label": ["Cross-Claimant","X-Claimant"]
    },
    "Cross Defendant": {
        "label": "Cross Defendant",
        "alt_label": ["Cross-Defendant","X-Defendant"]
    },
    "Cross Plaintiff": {
        "label": "Cross Plaintiff",
        "alt_label": ["Cross-Plaintiff","X-Plaintiff"]
    },
    "Custodian": {
        "label": "Custodian"
    },
    "Third Party Custodian": {
        "label": "Third Party Custodian",
        "alt_label": ["ThirdParty Custodian","3rd Party Custodian","3rdParty Custodian","Third Pty Custodian","3rd Pty Custodian"]
    },
    "Debtor": {
        "label": "Debtor"
    },
    "Debtor In Possession": {
        "label": "Debtor In Possession",
        "alt_label": ["Debtor-in-Possess"]
    },
    "Examiner": {
        "label": "Examiner"
    },
    "Financial Advisor": {
        "label": "Financial Advisor"
    },
    "Foreign Representative": {
        "label": "Foreign Representative"
    },
    "Garnishee": {
        "label": "Garnishee"
    },
    "Health Care Ombudsman": {
        "label": "Health Care Ombudsman"
    },
    "In Re": {
        "label": "In Re",
        "alt_label": ["In Re:"]
    },
    "Interested Party": {
        "label": "Interested Party",
        "alt_label": ["Party of Interest"]
    },
    "Interim Trustee": {
        "label": "Interim Trustee"
    },
    "Interpleader": {
        "label": "Interpleader"
    },
    "Intervenor": {
        "label": "Intervenor"
    },
    "Intervenor Respondent": {
        "label": "Intervenor Respondent"
    },
    "Intervenor Defendant": {
        "label": "Intervenor Defendant",
        "alt_label": ["Intervenor-Defendant","Intervenor Dft","Defendant/Intervenor"]
    },
    "Intervenor Plaintiff": {
        "label": "Intervenor Plaintiff",
        "alt_label": ["Intervenor-Plaintiff"]
    },
    "Joint Debtor": {
        "label": "Joint Debtor"
    },
    "Judge": {
        "label": "Judge"
    },
    "Liquidator": {
        "label": "Liquidator"
    },
    "Material Witness": {
        "label": "Material Witness"
    },
    "Mediator": {
        "label": "Mediator"
    },
    "Miscellaneous Party": {
        "label": "Miscellaneous Party",
        "alt_label":["Miscellaneous"]
    },
    "Movant": {
        "label": "Movant"
    },
    "Non-Filing Spouse": {
        "label": "Non-Filing Spouse",
        "alt_label": ["NF Spouse","Non Filing Spouse"]
    },
    "Objector": {
        "label": "Objector"
    },
    "Other Professional": {
        "label": "Other Professional",
        "alt_label": ["Professional"]
    },
    "Partner": {
        "label": "Partner"
    },
    "Petitioner": {
        "label": "Petitioner"
    },
    "Petitioning Creditor": {
        "label": "Petitioning Creditor"
    },
    "Plaintiff": {
        "label": "Plaintiff"
    },
    "Realtor": {
        "label": "Realtor"
    },
    "Receiver": {
        "label": "Receiver"
    },
    "Respondent": {
        "label": "Respondent"
    },
    "Special Counsel": {
        "label": "Special Counsel"
    },
    "Special Master": {
        "label": "Special Master"
    },
    "Stockholder": {
        "label": "Stockholder"
    },
    "Successor Trustee": {
        "label": "Successor Trustee"
    },
    "Surveyor": {
        "label": "Surveyor"
    },
    "Taxpayer": {
        "label": "Taxpayer"
    },
    "Trustee": {
        "label": "Trustee"
    },
    "U.S. Trustee": {
        "label": "U.S. Trustee",
        "alt_label": ["US Trustee"]
    },
    "Witness ": {
        "label": "Witness ",
        "alt_label": ["Witness"]
    },
    "Consolidated Third Party Defendant": {
        "label": "Consolidated Third Party Defendant",
        "alt_label": ["Consol Third Party Defendant","Consolidated ThirdParty Defendant","Consolidated 3rd Party Defendant","Consolidated 3rdParty Defendant","Consol ThirdParty Defendant","Consol 3rd Party Defendant","Consol 3rdParty Defendant"]
    },
    "Fourth Party Defendant": {
        "label": "Fourth Party Defendant",
        "alt_label": ["4th Party Defendant","FourthParty Defendant"]
    },
    "Fourth Party Plaintiff": {
        "label": "Fourth Party Plaintiff",
        "alt_label": ["4th Party Plaintiff","FourthParty Plaintiff"]
    },
    "Interested Non-Party": {
        "label": "Interested Non-Party"
    },
    "Notice Party": {
        "label": "Notice Party",
        "alt_label": ["Notice Only Party","BK Notice Party","Notice Only"]
    },
    "Garnishee": {
        "label": "Garnishee"
    },
    "Movant": {
        "label": "Movant"
    },
    "Unknown": {
        "label": "unknown"
    },
    "Surety": {
        "label": "Surety"
    },
    "Interpreter": {
        "label": "Interpreter"
    },
    "Estate Plaintiff": {
        "label": "Estate Plaintiff",
        "alt_label": ["Plaintiff - Estate"]
    },
    "Estate Defendant": {
        "label": "Estate Defendant",
        "alt_label": ["Estate-Defendant","Defendant - Estate"]
    },
    "Relief Defendant": {
        "label": "Relief Defendant"
    },
    "Executor Defendant": {
        "label": "Executor Defendant",
        "alt_label": ["Executor-Defendant"]
    },
    "Executor Plaintiff": {
        "label": "Executor Plaintiff"
    },
    "Estate of": {
        "label": "Estate of"
    },
    "Mediation Assistance Program Counsel": {
        "label": "Mediation Assistance Program Counsel"
    },
    "Recruited Counsel": {
        "label": "Recruited Counsel"
    },
    "Relator": {
        "label": "Relator"
    },
    "Deponent": {
        "label": "Deponent"
    },
    "Proposed": {
        "label": "Proposed"
    },
    "Court Monitor": {
        "label": "Court Monitor"
    },
    "Habeas Attorney General Service List": {
        "label": "Habeas Attorney General Service List"
    },
    "Real Party In Interest Defendant": {
        "label": "Real Party In Interest Defendant",
        "alt_label": ["Real Party In Interest Dft"]
    },
    "Neutral": {
        "label": "Neutral"
    },
    "Guardian Ad Litem Party": {
        "label": "Guardian Ad Litem Party",
        "alt_label": ["Guardian Ad Litem","Attorney/Guardian Ad Litem"]
    },
    "Guardian Ad Litem Plaintiff": {
        "label": "Guardian Ad Litem Plaintiff",
        "alt_label": ["Guardian ad Litem Plaintiff"]
    },
    "Referee": {
        "label": "Referee"
    },
    "ADR Provider": {
        "label": "ADR Provider",
        "alt_label": ["Adr Provider"]
    },
    "All Defendants": {
        "label": "All Defendants"
    },
    "Defendant-in-Rem": {
        "label": "Defendant-in-Rem",
        "alt_label": ["Defendant-In-Rem"]
    },
    "All Plaintiffs": {
        "label": "All Plaintiffs"
    },
    "Nominal Defendant": {
        "label": "Nominal Defendant"
    },
    "Consolidated Appellant": {
        "label": "Consolidated Appellant",
        "alt_label": ["Consol Appellant"]
    },
    "Consolidated Appellee": {
        "label": "Consolidated Appellee",
        "alt_label": ["Consol Appellee"]
    },
    "Interpleader Defendant": {
        "label": "Interpleader Defendant"
    },
    "Interpleader Plaintiff": {
        "label": "Interpleader Plaintiff"
    },
    "Consolidated Petitioner": {
        "label": "Consolidated Petitioner",
        "alt_label": ["Consol Petitioner"]
    },
    "Coordinating Discovery Attorney": {
        "label": "Coordinating Discovery Attorney"
    },
    "Applicant": {
        "label": "Applicant"
    },
    "Special Mediation Counsel": {
        "label": "Special Mediation Counsel"
    },
    "Technical Advisor": {
        "label": "Technical Advisor"
    },
    "Bankruptcy Judge": {
        "label": "Bankruptcy Judge"
    },
    "Responsible Third Party": {
        "label": "Responsible Third Party",
        "alt_label": ["Responsible 3rd Party","Responsible ThirdParty"]
    },
    "Conservator": {
        "label": "Conservator"
    },
    "Plaintiff, Counter Defendant": {
        "label": "Plaintiff, Counter Defendant"
    },
    "Defendant, Counter Plaintiff": {
        "label": "Defendant, Counter Plaintiff"
    },
    "Involuntary Plaintiff": {
        "label": "Involuntary Plaintiff",
        "alt_label": ["Involuntary-Plaintiff"]
    },
    "Reach and Apply Defendant": {
        "label": "Reach and Apply Defendant"
    },
    "Defaulted Party": {
        "label": "Defaulted Party"
    },
    "Defaulted Defendant": {
        "label": "Defaulted Defendant",
        "alt_label": ["Defendant - Defaulted"]
    },
    "Trustee in Bankruptcy": {
        "label": "Trustee in Bankruptcy"
    },
    "Master Commissioner": {
        "label": "Master Commissioner"
    },
    "Defendant/Appellee": {
        "label": "Defendant/Appellee"
    },
    "Defendant/Appellant": {
        "label": "Defendant/Appellant"
    },
    "Plaintiff/Appellant": {
        "label": "Plaintiff/Appellant"
    },
    "Case Evaluator": {
        "label": "Case Evaluator"
    },
    "Case Evaluator Chair": {
        "label": "Case Evaluator Chair"
    },
    "ENE Evaluator": {
        "label": "ENE Evaluator",
        "alt_label": ["Ene Evaluator"]
    },
    "Disinterested Person": {
        "label": "Disinterested Person"
    },
    "Counterclaim Plaintiff": {
        "label": "Counterclaim Plaintiff"
    },
    "Counterclaim Defendant": {
        "label": "Counterclaim Defendant"
    },
    "Prisoner Litigation Settlement Program": {
        "label": "Prisoner Litigation Settlement Program"
    },
    "PLSP Attorney Appointed for Plaintiff": {
        "label": "PLSP Attorney Appointed for Plaintiff",
        "alt_label": ["Plsp Attorney Appointed For Plaintiff"]
    },
    "Carrier": {
        "label": "Carrier"
    },
    "Unnamed Defendant": {
        "label": "Unnamed Defendant"
    },
    "Lead Defendant": {
        "label": "Lead Defendant"
    },
    "Official Defendant": {
        "label": "Official Defendant"
    },
    "Other Party": {
        "label": "Other Party"
    },
    "Non-Party": {
        "label": "Non-Party",
        "alt_label": ["Non Party"]
    },
    "Substitute Custodian": {
        "label": "Substitute Custodian"
    },
    "Relator Plaintiff": {
        "label": "Relator Plaintiff"
    },
    "Apportionment Defendant": {
        "label": "Apportionment Defendant"
    },
    "Requesting Party": {
        "label": "Requesting Party"
    },
    "Objecting Party": {
        "label": "Objecting Party"
    },
    "Underinsured Motorist Carrier": {
        "label": "Underinsured Motorist Carrier"
    },
    "ADR Limited Scope Counsel": {
        "label": "ADR Limited Scope Counsel",
        "alt_label": ["Adr Limited Scope Counsel"]
    },
    "Ex Rel.": {
        "label": "Ex Rel."
    }
}
